<?xml version="1.0" encoding="utf-8" standalone="yes"?><!-- Generated by abcexcel-->

<rec>
   <Records>
       <المحصول>
       <Row ty='M' id="0" type='الفاكهة'>نخيل البلح</Row>
       <Row ty='M' id="1" type='الفاكهة'>الزيتون</Row>
       <Row ty='M' id="2" type='الفاكهة'>العنب</Row>
       <Row ty='M' id="3" type='الفاكهة'>الحمضيات</Row>
       <Row ty='M' id="4" type='الفاكهة'>التين</Row>
       <Row ty='M' id="5" type='الفاكهة'>خوخ</Row>
       <Row ty='M' id="6" type='الفاكهة'>مشمش</Row>
       <Row ty='M' id="7" type='الفاكهة'>تفاح</Row>
       <Row ty='M' id="8" type='الفاكهة'>المانجو</Row>
       <Row ty='M' id="9" type='الفاكهة'>اشجار اخرى+اشجار مختلطة</Row>
       <Row ty='M' id="10" type='الفاكهة'>الورد</Row>

       <Row ty='M' id="11" type='الحبوب'>القمح</Row>
       <Row ty='M' id="12" type='الحبوب'>الشعير</Row>
       <Row ty='M' id="13" type='الحبوب'>الذرة الشامية</Row>
       <Row ty='M' id="14" type='الحبوب'>الذرة الرفيعة</Row>


       <Row ty='M' id="15" type='الاعلاف'>البرسيم</Row>
       <Row ty='M' id="16" type='الاعلاف'>الرودس</Row>

       <Row ty='M' id="17" type='الشتوية'>الطماطم</Row>
       <Row ty='M' id="18" type='الشتوية'>الكوسا</Row>
       <Row ty='M' id="19" type='الشتوية'>بطاطس</Row>
       <Row ty='M' id="20" type='الشتوية'>الفاصوليا</Row>
       <Row ty='M' id="21" type='الشتوية'>الفلفل</Row>
       <Row ty='M' id="22" type='الشتوية'>الباذنجان</Row>
       <Row ty='M' id="23" type='الشتوية'>ملفوف</Row>
       <Row ty='M' id="24" type='الشتوية'>بصل</Row>
       <Row ty='M' id="25" type='الشتوية'>جزر</Row>
       <Row ty='M' id="26" type='الشتوية'>قرنبيط</Row>
       <Row ty='M' id="27" type='الشتوية'>خضراوات ورقية اخرى</Row>

       <Row ty='M' id="28" type='الصيفية'>الطماطم</Row>
       <Row ty='M' id="29" type='الصيفية'>بطاطس</Row>
       <Row ty='M' id="30" type='الصيفية'>الفاصوليا</Row>
       <Row ty='M' id="31" type='الصيفية'>الباميا</Row>
       <Row ty='M' id="32" type='الصيفية'>الفلفل</Row>
       <Row ty='M' id="33" type='الصيفية'>بصل</Row>
       <Row ty='M' id="34" type='الصيفية'>بطيخ</Row>
       <Row ty='M' id="35" type='الصيفية'>الشمام</Row>
       <Row ty='M' id="36" type='الصيفية'>ملفوف</Row>
       <Row ty='M' id="37" type='الصيفية'>الباذنجان</Row>
       <Row ty='M' id="38" type='الصيفية'>قرع</Row>
       <Row ty='M' id="39" type='الصيفية'>خيار</Row>
       <Row ty='M' id="40" type='الصيفية'>خضراوات ورقية اخرى</Row>
       <Row ty='M' id="41" type='الصيفية'>النعناع</Row>

       <Row ty='M' id="42" type='محمية'>الطماطم</Row>
       <Row ty='M' id="43" type='محمية'>الكوسا</Row>
       <Row ty='M' id="44" type='محمية'>الباذنجان</Row>
       <Row ty='M' id="45" type='محمية'>الخيار</Row>
       <Row ty='M' id="46" type='محمية'>الفلفل</Row>
       <Row ty='M' id="47" type='محمية'>الباميا</Row>
       <Row ty='M' id="48" type='محمية'>الخضروات الاخرى</Row>

       </المحصول>

      <تبوك>
       <Row ty='M' id="نخيل البلح">1234.3</Row>
       <Row ty='M' id="الزيتون">1918.1</Row>
       <Row ty='M' id="العنب">1421.8</Row>
       <Row ty='M' id="الحمضيات">494.7</Row>
       <Row ty='M' id="التين">23.3</Row>
       <Row ty='M' id="الرمان">337.3</Row>
       <Row ty='M' id="خوخ">579.5</Row>
       <Row ty='M' id="مشمش">298.3</Row>
       <Row ty='M' id="تفاح">25.0</Row>
       <Row ty='M' id="المانجو">9.6</Row>
       <Row ty='M' id="اشجار اخرى+اشجار مختلطة">96.8</Row>
       <Row ty='M' id="الورد">1.75</Row>


       <Row ty='M' id="القمح">6788.7</Row>
       <Row ty='M' id="الشعير">1429.6</Row>
       <Row ty='M' id="الذرة الشامية">684.6</Row>
       <Row ty='M' id="الذرة الرفيعة">904.3 </Row>

       <Row ty='M' id="البرسيم">10934.0</Row>
       <Row ty='M' id="الرودس">112.0</Row>
   

       <Row ty='M' id="الطماطم">101.97</Row>
       <Row ty='M' id="الكوسا">0</Row>
       <Row ty='M' id="البطاطس">868.54</Row>
       <Row ty='M' id="الفاصوليا">4.26</Row>
       <Row ty='M' id="الفلفل">0</Row>
       <Row ty='M' id="الباذنجان">3.27</Row>
       <Row ty='M' id="ملفوف">21.95</Row>
       <Row ty='M' id="بصل">155.87</Row>
       <Row ty='M' id="جزر">14.85</Row>
       <Row ty='M' id="قرنبيط">32.27</Row>
       <Row ty='M' id="الخضروات الورقية">80.34 </Row>


       <Row ty='M' id="الطماطم">285.38</Row>
       <Row ty='M' id="بطاطس">673.61</Row>
       <Row ty='M' id="الفاصوليا">5.93</Row>
       <Row ty='M' id="الباميا">9.03</Row>
       <Row ty='M' id="الفلفل">58.04</Row>
       <Row ty='M' id="البصل">340</Row>
       <Row ty='M' id="البطيخ">126.74</Row>
       <Row ty='M' id="الشمام">14.98</Row>
       <Row ty='M' id="ملفوف">0</Row>
       <Row ty='M' id="الباذنجان">25.94</Row>
       <Row ty='M' id="القرع">38.66</Row>
       <Row ty='M' id="خيار">20.96</Row>
       <Row ty='M' id="الخضروات الورقيةاخرى">39.38</Row>
       <Row ty='M' id="النعناع">1.07</Row>


       <Row ty='M' id="الطماطم">130.21</Row>
       <Row ty='M' id="الكوسا">69.27</Row>
       <Row ty='M' id="الباذنجان">44.32</Row>
       <Row ty='M' id="الخيار">225.26</Row>
       <Row ty='M' id="الفلفل">113.08</Row>
       <Row ty='M' id="الخضروات الاخرى">25.85</Row>


      </تبوك>

        
      <الوجه>
       <Row ty='M' id="نخيل البلح">59.8</Row>
       <Row ty='M' id="الزيتون">0</Row>
       <Row ty='M' id="العنب">0</Row>
       <Row ty='M' id="الحمضيات">1.9</Row>
       <Row ty='M' id="التين">0</Row>
       <Row ty='M' id="الرمان">0</Row>
       <Row ty='M' id="خوخ">0</Row>
       <Row ty='M' id="مشمش">0</Row>
       <Row ty='M' id="تفاح">0</Row>
       <Row ty='M' id="المانجو">2.8</Row>
       <Row ty='M' id="اشجار اخرى+اشجار مختلطة">0</Row>
       <Row ty='M' id="الورد">0</Row>
       <Row ty='M' id="القمح">0.4</Row>
       <Row ty='M' id="الشعير">0.4</Row>
       <Row ty='M' id="الذرة الشامية">0</Row>
       <Row ty='M' id="الذرة الرفيعة">0 </Row>

       <Row ty='M' id="البرسيم">0</Row>
       <Row ty='M' id="الرودس">0</Row>
   

       <Row ty='M' id="الطماطم">1.5</Row>
       <Row ty='M' id="الكوسا">0.58</Row>
       <Row ty='M' id="البطاطس">0</Row>
       <Row ty='M' id="الفاصوليا">0</Row>
       <Row ty='M' id="الفلفل">0.83</Row>
       <Row ty='M' id="الباذنجان">0.58</Row>
       <Row ty='M' id="ملفوف">0</Row>
       <Row ty='M' id="بصل">0</Row>
       <Row ty='M' id="جزر">0.3</Row>
       <Row ty='M' id="قرنبيط">0.82</Row>
       <Row ty='M' id="الخضروات الورقية">0.62 </Row>


       <Row ty='M' id="الطماطم">0.38</Row>
       <Row ty='M' id="بطاطس">0</Row>
       <Row ty='M' id="الفاصوليا">0</Row>
       <Row ty='M' id="الباميا">0.3</Row>
       <Row ty='M' id="الفلفل">0.4</Row>
       <Row ty='M' id="البصل">0</Row>
       <Row ty='M' id="البطيخ">0.5</Row>
       <Row ty='M' id="الشمام">0</Row>
       <Row ty='M' id="ملفوف">0</Row>
       <Row ty='M' id="الباذنجان">0.32</Row>
       <Row ty='M' id="القرع">0</Row>
       <Row ty='M' id="خيار">0</Row>
       <Row ty='M' id="الخضروات الورقيةاخرى">1.14</Row>
       <Row ty='M' id="النعناع">0</Row>


       <Row ty='M' id="الطماطم">0</Row>
       <Row ty='M' id="الكوسا">0</Row>
       <Row ty='M' id="الباذنجان">0</Row>
       <Row ty='M' id="الخيار">0</Row>
       <Row ty='M' id="الفلفل">0</Row>
       <Row ty='M' id="الخضروات الاخرى">0</Row>


       </الوجه>



        



     <ضباء>
       <Row ty='M' id="نخيل البلح">501.4</Row>
       <Row ty='M' id="الزيتون">4.7</Row>
       <Row ty='M' id="العنب">0.1</Row>
       <Row ty='M' id="الحمضيات">95.8</Row>
       <Row ty='M' id="التين">0</Row>
       <Row ty='M' id="الرمان">0.1</Row>
       <Row ty='M' id="خوخ">4.0</Row>
       <Row ty='M' id="مشمش">3.0</Row>
       <Row ty='M' id="تفاح">0</Row>
       <Row ty='M' id="المانجو">78.3</Row>
       <Row ty='M' id="اشجار اخرى+اشجار مختلطة">11.8</Row>
       <Row ty='M' id="الورد">0</Row>


       <Row ty='M' id="القمح">5.9</Row>
       <Row ty='M' id="الشعير">6.0</Row>
       <Row ty='M' id="الذرة الشامية">14.1</Row>
       <Row ty='M' id="الذرة الرفيعة">1.2 </Row>

       <Row ty='M' id="البرسيم">0</Row>
       <Row ty='M' id="الرودس">0</Row>
   

       <Row ty='M' id="الطماطم">78.7</Row>
       <Row ty='M' id="الكوسا">2.69</Row>
       <Row ty='M' id="البطاطس">3.77</Row>
       <Row ty='M' id="الفاصوليا">5.24</Row>
       <Row ty='M' id="الفلفل">9.59</Row>
       <Row ty='M' id="الباذنجان">21.75</Row>
       <Row ty='M' id="ملفوف">4.81</Row>
       <Row ty='M' id="بصل">5.05</Row>
       <Row ty='M' id="جزر">0.64</Row>
       <Row ty='M' id="قرنبيط">56.44</Row>
       <Row ty='M' id="الخضروات الورقية">56.53 </Row>


       <Row ty='M' id="الطماطم">43.91</Row>
       <Row ty='M' id="بطاطس">6.59</Row>
       <Row ty='M' id="الفاصوليا">6.08</Row>
       <Row ty='M' id="الباميا">4.72</Row>
       <Row ty='M' id="الفلفل">14.6</Row>
       <Row ty='M' id="البصل">8.52</Row>
       <Row ty='M' id="البطيخ">30.49</Row>
       <Row ty='M' id="الشمام">2.95</Row>
       <Row ty='M' id="ملفوف">6.61</Row>
       <Row ty='M' id="الباذنجان">17.6</Row>
       <Row ty='M' id="القرع">17.09</Row>
       <Row ty='M' id="خيار">9.63</Row>
       <Row ty='M' id="الخضروات الورقيةاخرى">56.84</Row>
       <Row ty='M' id="النعناع">0</Row>


       <Row ty='M' id="الطماطم">0</Row>
       <Row ty='M' id="الكوسا">0</Row>
       <Row ty='M' id="الباذنجان">0</Row>
       <Row ty='M' id="الخيار">0</Row>
       <Row ty='M' id="الفلفل">0</Row>
       <Row ty='M' id="الخضروات الاخرى">0</Row>


      </ضباء>



      <تيماء>
       <Row ty='M' id="نخيل البلح">913.5</Row>
       <Row ty='M' id="الزيتون">1918.1</Row>
       <Row ty='M' id="العنب">23.3</Row>
       <Row ty='M' id="الحمضيات">25.5</Row>
       <Row ty='M' id="التين">0.1</Row>
       <Row ty='M' id="الرمان">5.3</Row>
       <Row ty='M' id="خوخ">22.0</Row>
       <Row ty='M' id="مشمش">10.0</Row>
       <Row ty='M' id="تفاح">0</Row>
       <Row ty='M' id="المانجو">-</Row>
       <Row ty='M' id="اشجار اخرى+اشجار مختلطة">1.8</Row>
       <Row ty='M' id="الورد">0.18</Row>


       <Row ty='M' id="القمح">108.4</Row>
       <Row ty='M' id="الشعير">230.6</Row>
       <Row ty='M' id="الذرة الشامية">71.4</Row>
       <Row ty='M' id="الذرة الرفيعة">61.9 </Row>

       <Row ty='M' id="البرسيم">0</Row>
       <Row ty='M' id="الرودس">0</Row>
   

       <Row ty='M' id="الطماطم">16.62</Row>
       <Row ty='M' id="الكوسا">3.79</Row>
       <Row ty='M' id="البطاطس">98.55</Row>
       <Row ty='M' id="الفاصوليا">0</Row>
       <Row ty='M' id="الفلفل">0</Row>
       <Row ty='M' id="الباذنجان">1.17</Row>
       <Row ty='M' id="ملفوف">1.27</Row>
       <Row ty='M' id="بصل">26.19</Row>
       <Row ty='M' id="جزر">14.24</Row>
       <Row ty='M' id="قرنبيط">16.60</Row>
       <Row ty='M' id="الخضروات الورقية">2.22 </Row>


       <Row ty='M' id="الطماطم">12.13</Row>
       <Row ty='M' id="بطاطس">0</Row>
       <Row ty='M' id="الفاصوليا">0</Row>
       <Row ty='M' id="الباميا">0</Row>
       <Row ty='M' id="الفلفل">2.31</Row>
       <Row ty='M' id="البصل">11.98</Row>
       <Row ty='M' id="البطيخ">0</Row>
       <Row ty='M' id="الشمام">0</Row>
       <Row ty='M' id="ملفوف">0</Row>
       <Row ty='M' id="الباذنجان">0.43</Row>
       <Row ty='M' id="القرع">0</Row>
       <Row ty='M' id="خيار">25.88</Row>
       <Row ty='M' id="الخضروات الورقيةاخرى">0</Row>
       <Row ty='M' id="النعناع">0</Row>


       <Row ty='M' id="الطماطم">11.01</Row>
       <Row ty='M' id="الكوسا">1.34</Row>
       <Row ty='M' id="الباذنجان">0.60</Row>
       <Row ty='M' id="الخيار">4.51</Row>
       <Row ty='M' id="الفلفل">0</Row>
       <Row ty='M' id="الخضروات الاخرى">0</Row>
        </تيماء>




      <املج>
       <Row ty='M' id="نخيل البلح">96.6</Row>
       <Row ty='M' id="الزيتون">3.5</Row>
       <Row ty='M' id="العنب">0.6</Row>
       <Row ty='M' id="الحمضيات">9.5</Row>
       <Row ty='M' id="التين">0</Row>
       <Row ty='M' id="الرمان">0.6</Row>
       <Row ty='M' id="خوخ">0</Row>
       <Row ty='M' id="مشمش">0</Row>
       <Row ty='M' id="تفاح">0</Row>
       <Row ty='M' id="المانجو">105.1</Row>
       <Row ty='M' id="اشجار اخرى+اشجار مختلطة">26.1</Row>
       <Row ty='M' id="الورد">0</Row>


       <Row ty='M' id="القمح">0</Row>
       <Row ty='M' id="الشعير">0</Row>
       <Row ty='M' id="الذرة الشامية">1.3</Row>
       <Row ty='M' id="الذرة الرفيعة">0.1 </Row>

      <Row ty='M' id="البرسيم">0</Row>
       <Row ty='M' id="الرودس">0</Row>

       <Row ty='M' id="الطماطم">1.5</Row>
       <Row ty='M' id="الكوسا">0</Row>
       <Row ty='M' id="البطاطس">0</Row>
       <Row ty='M' id="الفاصوليا">0</Row>
       <Row ty='M' id="الفلفل">0.52</Row>
       <Row ty='M' id="الباذنجان">0.48</Row>
       <Row ty='M' id="ملفوف">0</Row>
       <Row ty='M' id="بصل">0</Row>
       <Row ty='M' id="جزر">0</Row>
       <Row ty='M' id="قرنبيط">2.03</Row>
       <Row ty='M' id="الخضروات الورقية">0 </Row>


       <Row ty='M' id="الطماطم">0.68</Row>
       <Row ty='M' id="بطاطس">0</Row>
       <Row ty='M' id="الفاصوليا">0</Row>
       <Row ty='M' id="الباميا">0.42</Row>
       <Row ty='M' id="الفلفل">0.29</Row>
       <Row ty='M' id="البصل">0</Row>
       <Row ty='M' id="البطيخ">0</Row>
       <Row ty='M' id="الشمام">0</Row>
       <Row ty='M' id="ملفوف">0</Row>
       <Row ty='M' id="الباذنجان">0.49</Row>
       <Row ty='M' id="القرع">0.69</Row>
       <Row ty='M' id="خيار">0</Row>
       <Row ty='M' id="الخضروات الورقيةاخرى">1.61</Row>
       <Row ty='M' id="النعناع">0</Row>


       <Row ty='M' id="الطماطم">130.21</Row>
       <Row ty='M' id="الكوسا">69.27</Row>
       <Row ty='M' id="الباذنجان">44.32</Row>
       <Row ty='M' id="الخيار">225.26</Row>
       <Row ty='M' id="الفلفل">113.08</Row>
       <Row ty='M' id="الخضروات الاخرى">25.85</Row>


       </املج>

      <البدع>
       <Row ty='M' id="نخيل البلح">262.0</Row>
       <Row ty='M' id="الزيتون">65.0</Row>
       <Row ty='M' id="العنب">64.1</Row>
       <Row ty='M' id="الحمضيات">61.3</Row>
       <Row ty='M' id="التين">0.4</Row>
       <Row ty='M' id="الرمان">0.1</Row>
       <Row ty='M' id="خوخ">4.5</Row>
       <Row ty='M' id="مشمش">3.0</Row>
       <Row ty='M' id="تفاح">0</Row>
       <Row ty='M' id="المانجو">12.6</Row>
       <Row ty='M' id="اشجار اخرى+اشجار مختلطة">19.5</Row>
       <Row ty='M' id="الورد">0</Row>


       <Row ty='M' id="القمح">3.7</Row>
       <Row ty='M' id="الشعير">2.8</Row>
       <Row ty='M' id="الذرة الشامية">1.0</Row>
       <Row ty='M' id="الذرة الرفيعة">904.31.0 </Row>



       <Row ty='M' id="البرسيم">0</Row>
       <Row ty='M' id="الرودس">0</Row>



       <Row ty='M' id="الطماطم">5.55</Row>
       <Row ty='M' id="الكوسا">2.78</Row>
       <Row ty='M' id="البطاطس">1.76</Row>
       <Row ty='M' id="الفاصوليا">1.69</Row>
       <Row ty='M' id="الفلفل">0.5</Row>
       <Row ty='M' id="الباذنجان">0.88</Row>
       <Row ty='M' id="ملفوف">0.65</Row>
       <Row ty='M' id="بصل">1.42</Row>
       <Row ty='M' id="جزر">1.54</Row>
       <Row ty='M' id="قرنبيط">20.87</Row>
       <Row ty='M' id="الخضروات الورقية">0.06 </Row>


       <Row ty='M' id="الطماطم">21.35</Row>
       <Row ty='M' id="بطاطس">0</Row>
       <Row ty='M' id="الفاصوليا">0.4</Row>
       <Row ty='M' id="الباميا">1.31</Row>
       <Row ty='M' id="الفلفل">2.65</Row>
       <Row ty='M' id="البصل">0.71</Row>
       <Row ty='M' id="البطيخ">4.43</Row>
       <Row ty='M' id="الشمام">0.76</Row>
       <Row ty='M' id="ملفوف">0.44</Row>
       <Row ty='M' id="الباذنجان">5.57</Row>
       <Row ty='M' id="القرع">0.97</Row>
       <Row ty='M' id="خيار">1.85</Row>
       <Row ty='M' id="الخضروات الورقيةاخرى">3.67</Row>
       <Row ty='M' id="النعناع">0.26</Row>


       <Row ty='M' id="الطماطم">0.81</Row>
       <Row ty='M' id="الكوسا">0</Row>
       <Row ty='M' id="الباذنجان">0</Row>
       <Row ty='M' id="الخيار">0.16</Row>
       <Row ty='M' id="الفلفل">0</Row>
       <Row ty='M' id="الخضروات الاخرى">0.05</Row>


       </البدع>




      <حقل>
       <Row ty='M' id="نخيل البلح">8.6</Row>
       <Row ty='M' id="الزيتون">0</Row>
       <Row ty='M' id="العنب">0</Row>
       <Row ty='M' id="الحمضيات">-</Row>
       <Row ty='M' id="التين">0</Row>
       <Row ty='M' id="الرمان">0</Row>
       <Row ty='M' id="خوخ">0</Row>
       <Row ty='M' id="مشمش">0</Row>
       <Row ty='M' id="تفاح">0</Row>
       <Row ty='M' id="المانجو">0</Row>
       <Row ty='M' id="اشجار اخرى+اشجار مختلطة">0</Row>
       <Row ty='M' id="الورد">0</Row>


       <Row ty='M' id="القمح">0</Row>
       <Row ty='M' id="الشعير">0</Row>
       <Row ty='M' id="الذرة الشامية">0</Row>
       <Row ty='M' id="الذرة الرفيعة">0 </Row>

       <Row ty='M' id="البرسيم">0</Row>
       <Row ty='M' id="الرودس">0</Row>

       <Row ty='M' id="الطماطم">0</Row>
       <Row ty='M' id="الكوسا">0</Row>
       <Row ty='M' id="البطاطس">0</Row>
       <Row ty='M' id="الفاصوليا">0</Row>
       <Row ty='M' id="الفلفل">0</Row>
       <Row ty='M' id="الباذنجان">0</Row>
       <Row ty='M' id="ملفوف">0</Row>
       <Row ty='M' id="بصل">0</Row>
       <Row ty='M' id="جزر">0</Row>
       <Row ty='M' id="قرنبيط">0</Row>
       <Row ty='M' id="الخضروات الورقية">0 </Row>


       <Row ty='M' id="الطماطم">0</Row>
       <Row ty='M' id="بطاطس">0</Row>
       <Row ty='M' id="الفاصوليا">0</Row>
       <Row ty='M' id="الباميا">0</Row>
       <Row ty='M' id="الفلفل">0</Row>
       <Row ty='M' id="البصل">0</Row>
       <Row ty='M' id="البطيخ">0</Row>
       <Row ty='M' id="الشمام">0</Row>
       <Row ty='M' id="ملفوف">0</Row>
       <Row ty='M' id="الباذنجان">0</Row>
       <Row ty='M' id="القرع">0</Row>
       <Row ty='M' id="خيار">0</Row>
       <Row ty='M' id="الخضروات الورقيةاخرى">0</Row>
       <Row ty='M' id="النعناع">0</Row>


       <Row ty='M' id="الطماطم">0</Row>
       <Row ty='M' id="الكوسا">0</Row>
       <Row ty='M' id="الباذنجان">0</Row>
       <Row ty='M' id="الخيار">0</Row>
       <Row ty='M' id="الفلفل">0</Row>
       <Row ty='M' id="الخضروات الاخرى">0</Row>


       </حقل>





   </Records> 

   <Records>


    
       
       <المحصول>
       <Row ty='W' id="0">نخيل البلح</Row>
       <Row ty='W' id="1">الزيتون</Row>
       <Row ty='W' id="2">العنب</Row>
       <Row ty='W' id="3">الحمضيات</Row>
       <Row ty='W' id="4">التين</Row>
       <Row ty='W' id="5">خوخ</Row>
       <Row ty='W' id="6">مشمش</Row>
       <Row ty='W' id="7">تفاح</Row>
       <Row ty='W' id="8">المانجو</Row>
       <Row ty='W' id="9">اشجار اخرى+اشجار مختلطة</Row>
       <Row ty='W' id="10">الورد</Row>

       <Row ty='W' id="11">القمح</Row>
       <Row ty='W' id="12">الشعير</Row>
       <Row ty='W' id="13">الذرة الشامية</Row>
       <Row ty='W' id="14">الذرة الرفيعة</Row>


       <Row ty='W' id="15">البرسيم</Row>
       <Row ty='W' id="16">الرودس</Row>

       <Row ty='W' id="17">الطماطم</Row>
       <Row ty='W' id="18">الكوسا</Row>
       <Row ty='W' id="19">بطاطس</Row>
       <Row ty='W' id="20">الفاصوليا</Row>
       <Row ty='W' id="21">الفلفل</Row>
       <Row ty='W' id="22">الباذنجان</Row>
       <Row ty='W' id="23">ملفوف</Row>
       <Row ty='W' id="24">بصل</Row>
       <Row ty='W' id="25">جزر</Row>
       <Row ty='W' id="26">قرنبيط</Row>
       <Row ty='W' id="27">خضراوات ورقية اخرى</Row>

       <Row ty='W' id="28">الطماطم</Row>
       <Row ty='W' id="29">بطاطس</Row>
       <Row ty='W' id="30">الفاصوليا</Row>
       <Row ty='W' id="31">الباميا</Row>
       <Row ty='W' id="32">الفلفل</Row>
       <Row ty='W' id="33">بصل</Row>
       <Row ty='W' id="34">بطيخ</Row>
       <Row ty='W' id="35">الشمام</Row>
       <Row ty='W' id="36">ملفوف</Row>
       <Row ty='W' id="37">الباذنجان</Row>
       <Row ty='W' id="38">قرع</Row>
       <Row ty='W' id="39">خيار</Row>
       <Row ty='W' id="40">خضراوات ورقية اخرى</Row>
       <Row ty='W' id="41">النعناع</Row>

       <Row ty='W' id="42">الطماطم</Row>
       <Row ty='W' id="43">الكوسا</Row>
       <Row ty='W' id="44">الباذنجان</Row>
       <Row ty='W' id="45">الخيار</Row>
       <Row ty='W' id="46">الفلفل</Row>
       <Row ty='W' id="47">الباميا</Row>
       <Row ty='W' id="48">الخضروات الاخرى</Row>

       </المحصول>
       <تبوك>
       <Row ty='W' id="نخيل البلح">11160</Row>
       <Row ty='W' id="الزيتون">5500</Row>
       <Row ty='W' id="العنب">7760</Row>
       <Row ty='W' id="الحمضيات">9500</Row>
       <Row ty='W' id="التين">7650</Row>
       <Row ty='W' id="الرمان">7550</Row>
       <Row ty='W' id="خوخ">7200</Row>
       <Row ty='W' id="مشمش">7200</Row>
       <Row ty='W' id="تفاح">7200</Row>
       <Row ty='W' id="المانجو">8740</Row>
       <Row ty='W' id="اشجار اخرى+اشجار مختلطة">8740</Row>
       <Row ty='W' id="الورد">5500</Row>


       <Row ty='W' id="القمح">6550</Row>
       <Row ty='W' id="الشعير">6200</Row>
       <Row ty='W' id="الذرة الشامية">8600</Row>
       <Row ty='W' id="الذرة الرفيعة">7500 </Row>

       <Row ty='W' id="البرسيم">30340</Row>
       <Row ty='W' id="الرودس">30120 </Row>

       <Row ty='W' id="الطماطم">6750</Row>
       <Row ty='W' id="الكوسا">0</Row>
       <Row ty='W' id="البطاطس">6480</Row>
       <Row ty='W' id="الفاصوليا">6660</Row>
       <Row ty='W' id="الفلفل">0</Row>
       <Row ty='W' id="الباذنجان">6390</Row>
       <Row ty='W' id="ملفوف">6300</Row>
       <Row ty='W' id="بصل">7110</Row>
       <Row ty='W' id="جزر">6750</Row>
       <Row ty='W' id="قرنبيط">6660</Row>
       <Row ty='W' id="الخضروات الورقية">7200 </Row>


       <Row ty='W' id="الطماطم">7650</Row>
       <Row ty='W' id="بطاطس">7560</Row>
       <Row ty='W' id="الفاصوليا">7650</Row>
       <Row ty='W' id="الباميا">7380</Row>
       <Row ty='W' id="الفلفل">6300</Row>
       <Row ty='W' id="البصل">8190</Row>
       <Row ty='W' id="البطيخ">7110</Row>
       <Row ty='W' id="الشمام">7200</Row>
       <Row ty='W' id="ملفوف">0</Row>
       <Row ty='W' id="الباذنجان">7470</Row>
       <Row ty='W' id="القرع">7020</Row>
       <Row ty='W' id="خيار">7110</Row>
       <Row ty='W' id="الخضروات الورقيةاخرى">7290</Row>
       <Row ty='W' id="النعناع">7000</Row>


       <Row ty='W' id="الطماطم">6500</Row>
       <Row ty='W' id="الكوسا">5500</Row>
       <Row ty='W' id="الباذنجان">6200</Row>
       <Row ty='W' id="الخيار">7000</Row>
       <Row ty='W' id="الفلفل">6200</Row>
       <Row ty='W' id="الخضروات الاخرى">6200</Row>

       </تبوك>


      <الوجه>
      <Row ty='W' id="نخيل البلح">12276</Row>
       <Row ty='W' id="الزيتون">0</Row>
       <Row ty='W' id="العنب">0</Row>
       <Row ty='W' id="الحمضيات">10450</Row>
       <Row ty='W' id="التين">0</Row>
       <Row ty='W' id="الرمان">0</Row>
       <Row ty='W' id="خوخ">0</Row>
       <Row ty='W' id="مشمش">0</Row>
       <Row ty='W' id="تفاح">0</Row>
       <Row ty='W' id="المانجو">9614</Row>
       <Row ty='W' id="اشجار اخرى+اشجار مختلطة">0</Row>
       <Row ty='W' id="الورد">0</Row>


       <Row ty='W' id="القمح">7205</Row>
       <Row ty='W' id="الشعير">6820</Row>
       <Row ty='W' id="الذرة الشامية">0</Row>
       <Row ty='W' id="الذرة الرفيعة">0 </Row>

       <Row ty='W' id="البرسيم">0</Row>
       <Row ty='W' id="الرودس">0 </Row>

       <Row ty='W' id="الطماطم">7425</Row>
       <Row ty='W' id="الكوسا">7227</Row>
       <Row ty='W' id="البطاطس">0</Row>
       <Row ty='W' id="الفاصوليا">0</Row>
       <Row ty='W' id="الفلفل">6138</Row>
       <Row ty='W' id="الباذنجان">7029</Row>
       <Row ty='W' id="ملفوف">0</Row>
       <Row ty='W' id="بصل">0</Row>
       <Row ty='W' id="جزر">7425</Row>
       <Row ty='W' id="قرنبيط">7326</Row>
       <Row ty='W' id="الخضروات الورقية">7920 </Row>


       <Row ty='W' id="الطماطم">8415</Row>
       <Row ty='W' id="بطاطس">0</Row>
       <Row ty='W' id="الفاصوليا">0</Row>
       <Row ty='W' id="الباميا">8118</Row>
       <Row ty='W' id="الفلفل">6930</Row>
       <Row ty='W' id="البصل">0</Row>
       <Row ty='W' id="البطيخ">7821</Row>
       <Row ty='W' id="الشمام">0</Row>
       <Row ty='W' id="ملفوف">0</Row>
       <Row ty='W' id="الباذنجان">8217</Row>
       <Row ty='W' id="القرع">0</Row>
       <Row ty='W' id="خيار">0</Row>
       <Row ty='W' id="الخضروات الورقيةاخرى">8019</Row>
       <Row ty='W' id="النعناع">0</Row>


       <Row ty='W' id="الطماطم">0</Row>
       <Row ty='W' id="الكوسا">0</Row>
       <Row ty='W' id="الباذنجان">0</Row>
       <Row ty='W' id="الخيار">0</Row>
       <Row ty='W' id="الفلفل">0</Row>
       <Row ty='W' id="الخضروات الاخرى">0</Row>

       </الوجه>







       <ضباء>
         
      <Row ty='W' id="نخيل البلح">12053</Row>
       <Row ty='W' id="الزيتون">5940</Row>
       <Row ty='W' id="العنب">8381</Row>
       <Row ty='W' id="الحمضيات">10260</Row>
       <Row ty='W' id="التين">0</Row>
       <Row ty='W' id="الرمان">8154</Row>
       <Row ty='W' id="خوخ">7776</Row>
       <Row ty='W' id="مشمش">7776</Row>
       <Row ty='W' id="تفاح">0</Row>
       <Row ty='W' id="المانجو">9439</Row>
       <Row ty='W' id="اشجار اخرى+اشجار مختلطة">9612</Row>
       <Row ty='W' id="الورد">0</Row>


       <Row ty='W' id="القمح">7074</Row>
       <Row ty='W' id="الشعير">6696</Row>
       <Row ty='W' id="الذرة الشامية">9288</Row>
       <Row ty='W' id="الذرة الرفيعة">8100 </Row>

       <Row ty='W' id="البرسيم">0</Row>
       <Row ty='W' id="الرودس">0 </Row>

       <Row ty='W' id="الطماطم">7290</Row>
       <Row ty='W' id="الكوسا">7095.6</Row>
       <Row ty='W' id="البطاطس">6998.4</Row>
       <Row ty='W' id="الفاصوليا">7192.8</Row>
       <Row ty='W' id="الفلفل">6026.4</Row>
       <Row ty='W' id="الباذنجان">6901.2</Row>
       <Row ty='W' id="ملفوف">6804</Row>
       <Row ty='W' id="بصل">7678.8</Row>
       <Row ty='W' id="جزر">7290</Row>
       <Row ty='W' id="قرنبيط">7192.8</Row>
       <Row ty='W' id="الخضروات الورقية">7776 </Row>


       <Row ty='W' id="الطماطم">8262</Row>
       <Row ty='W' id="بطاطس">8165</Row>
       <Row ty='W' id="الفاصوليا">8262</Row>
       <Row ty='W' id="الباميا">7970</Row>
       <Row ty='W' id="الفلفل">6804</Row>
       <Row ty='W' id="البصل">8845</Row>
       <Row ty='W' id="البطيخ">7679</Row>
       <Row ty='W' id="الشمام">7776</Row>
       <Row ty='W' id="ملفوف">7679</Row>
       <Row ty='W' id="الباذنجان">8068</Row>
       <Row ty='W' id="القرع">7582</Row>
       <Row ty='W' id="خيار">7679</Row>
       <Row ty='W' id="الخضروات الورقيةاخرى">7873</Row>
       <Row ty='W' id="النعناع">0</Row>


       <Row ty='W' id="الطماطم">0</Row>
       <Row ty='W' id="الكوسا">0</Row>
       <Row ty='W' id="الباذنجان">0</Row>
       <Row ty='W' id="الخيار">0</Row>
       <Row ty='W' id="الفلفل">0</Row>
       <Row ty='W' id="الخضروات الاخرى">0</Row>

       
       </ضباء>









       <تيماء>
         
      <Row ty='W' id="نخيل البلح">11383</Row>
       <Row ty='W' id="الزيتون">5610</Row>
       <Row ty='W' id="العنب">7915</Row>
       <Row ty='W' id="الحمضيات">9690</Row>
       <Row ty='W' id="التين">7803</Row>
       <Row ty='W' id="الرمان">7701</Row>
       <Row ty='W' id="خوخ">7344</Row>
       <Row ty='W' id="مشمش">7344</Row>
       <Row ty='W' id="تفاح">0</Row>
       <Row ty='W' id="المانجو">0</Row>
       <Row ty='W' id="اشجار اخرى+اشجار مختلطة">9078</Row>
       <Row ty='W' id="الورد">5610</Row>


       <Row ty='W' id="القمح">6681</Row>
       <Row ty='W' id="الشعير">6324</Row>
       <Row ty='W' id="الذرة الشامية">8772</Row>
       <Row ty='W' id="الذرة الرفيعة">7650 </Row>

       <Row ty='W' id="البرسيم">30946.8</Row>
       <Row ty='W' id="الرودس">30722.4 </Row>

       <Row ty='W' id="الطماطم">6885</Row>
       <Row ty='W' id="الكوسا">6701.4</Row>
       <Row ty='W' id="البطاطس">6609.6</Row>
       <Row ty='W' id="الفاصوليا">0</Row>
       <Row ty='W' id="الفلفل">0</Row>
       <Row ty='W' id="الباذنجان">6517.8</Row>
       <Row ty='W' id="ملفوف">6426</Row>
       <Row ty='W' id="بصل">7252.2</Row>
       <Row ty='W' id="جزر">6885</Row>
       <Row ty='W' id="قرنبيط">6793.2</Row>
       <Row ty='W' id="الخضروات الورقية">7344 </Row>


       <Row ty='W' id="الطماطم">7803</Row>
       <Row ty='W' id="بطاطس">0</Row>
       <Row ty='W' id="الفاصوليا">0</Row>
       <Row ty='W' id="الباميا">0</Row>
       <Row ty='W' id="الفلفل">6426</Row>
       <Row ty='W' id="البصل">8354</Row>
       <Row ty='W' id="البطيخ">0</Row>
       <Row ty='W' id="الشمام">0</Row>
       <Row ty='W' id="ملفوف">0</Row>
       <Row ty='W' id="الباذنجان">7619</Row>
       <Row ty='W' id="القرع">0</Row>
       <Row ty='W' id="خيار">7252</Row>
       <Row ty='W' id="الخضروات الورقيةاخرى">0</Row>
       <Row ty='W' id="النعناع">0</Row>


       <Row ty='W' id="الطماطم">6500</Row>
       <Row ty='W' id="الكوسا">5500</Row>
       <Row ty='W' id="الباذنجان">6200</Row>
       <Row ty='W' id="الخيار">7000</Row>
       <Row ty='W' id="الفلفل">0</Row>
       <Row ty='W' id="الخضروات الاخرى">0</Row>

       
       </تيماء>





       <املج>
      
      <Row ty='W' id="نخيل البلح">12611</Row>
       <Row ty='W' id="الزيتون">6215</Row>
       <Row ty='W' id="العنب">8769</Row>
       <Row ty='W' id="الحمضيات">10735</Row>
       <Row ty='W' id="التين">0</Row>
       <Row ty='W' id="الرمان">8532</Row>
       <Row ty='W' id="خوخ">0</Row>
       <Row ty='W' id="مشمش">0</Row>
       <Row ty='W' id="تفاح">0</Row>
       <Row ty='W' id="المانجو">7876</Row>
       <Row ty='W' id="اشجار اخرى+اشجار مختلطة">10057</Row>
       <Row ty='W' id="الورد">0</Row>


       <Row ty='W' id="القمح">0</Row>
       <Row ty='W' id="الشعير">0</Row>
       <Row ty='W' id="الذرة الشامية">9718</Row>
       <Row ty='W' id="الذرة الرفيعة">8475</Row>

       <Row ty='W' id="البرسيم">0</Row>
       <Row ty='W' id="الرودس">0 </Row>

       <Row ty='W' id="الطماطم">7627.5</Row>
       <Row ty='W' id="الكوسا">0</Row>
       <Row ty='W' id="البطاطس">0</Row>
       <Row ty='W' id="الفاصوليا">0</Row>
       <Row ty='W' id="الفلفل">6305.4</Row>
       <Row ty='W' id="الباذنجان">7220.7</Row>
       <Row ty='W' id="ملفوف">0</Row>
       <Row ty='W' id="بصل">0</Row>
       <Row ty='W' id="جزر">0</Row>
       <Row ty='W' id="قرنبيط">7525.8</Row>
       <Row ty='W' id="الخضروات الورقية">0 </Row>


       <Row ty='W' id="الطماطم">8645</Row>
       <Row ty='W' id="بطاطس">0</Row>
       <Row ty='W' id="الفاصوليا">0</Row>
       <Row ty='W' id="الباميا">8339</Row>
       <Row ty='W' id="الفلفل">7119</Row>
       <Row ty='W' id="البصل">0</Row>
       <Row ty='W' id="البطيخ">0</Row>
       <Row ty='W' id="الشمام">0</Row>
       <Row ty='W' id="ملفوف">0</Row>
       <Row ty='W' id="الباذنجان">8441</Row>
       <Row ty='W' id="القرع">7933</Row>
       <Row ty='W' id="خيار">0</Row>
       <Row ty='W' id="الخضروات الورقيةاخرى">8238</Row>
       <Row ty='W' id="النعناع">0</Row>


       <Row ty='W' id="الطماطم">0</Row>
       <Row ty='W' id="الكوسا">0</Row>
       <Row ty='W' id="الباذنجان">0</Row>
       <Row ty='W' id="الخيار">0</Row>
       <Row ty='W' id="الفلفل">0</Row>
       <Row ty='W' id="الخضروات الاخرى">0</Row>

      
       </املج>





         <البدع>
      <Row ty='W' id="نخيل البلح">11718</Row>
       <Row ty='W' id="الزيتون">5775</Row>
       <Row ty='W' id="العنب">8148</Row>
       <Row ty='W' id="الحمضيات">9975</Row>
       <Row ty='W' id="التين">8033</Row>
       <Row ty='W' id="الرمان">7928</Row>
       <Row ty='W' id="خوخ">7560</Row>
       <Row ty='W' id="مشمش">7560</Row>
       <Row ty='W' id="تفاح">0</Row>
       <Row ty='W' id="المانجو">9177</Row>
       <Row ty='W' id="اشجار اخرى+اشجار مختلطة">9345</Row>
       <Row ty='W' id="الورد">0</Row>


       <Row ty='W' id="القمح">6877.5</Row>
       <Row ty='W' id="الشعير">6510</Row>
       <Row ty='W' id="الذرة الشامية">9030</Row>
       <Row ty='W' id="الذرة الرفيعة">7875 </Row>

       <Row ty='W' id="البرسيم">0</Row>
       <Row ty='W' id="الرودس">0 </Row>

       <Row ty='W' id="الطماطم">7087.5</Row>
       <Row ty='W' id="الكوسا">6898.5</Row>
       <Row ty='W' id="البطاطس">6804</Row>
       <Row ty='W' id="الفاصوليا">6993</Row>
       <Row ty='W' id="الفلفل">5859</Row>
       <Row ty='W' id="الباذنجان">6709.5</Row>
       <Row ty='W' id="ملفوف">6615</Row>
       <Row ty='W' id="بصل">7465.5</Row>
       <Row ty='W' id="جزر">7087.5</Row>
       <Row ty='W' id="قرنبيط">6993</Row>
       <Row ty='W' id="الخضروات الورقية">7560 </Row>


       <Row ty='W' id="الطماطم">8033</Row>
       <Row ty='W' id="بطاطس">0</Row>
       <Row ty='W' id="الفاصوليا">8033</Row>
       <Row ty='W' id="الباميا">7749</Row>
       <Row ty='W' id="الفلفل">6615</Row>
       <Row ty='W' id="البصل">8600</Row>
       <Row ty='W' id="البطيخ">7466</Row>
       <Row ty='W' id="الشمام">7560</Row>
       <Row ty='W' id="ملفوف">7466</Row>
       <Row ty='W' id="الباذنجان">7844</Row>
       <Row ty='W' id="القرع">7371</Row>
       <Row ty='W' id="خيار">7466</Row>
       <Row ty='W' id="الخضروات الورقيةاخرى">7655</Row>
       <Row ty='W' id="النعناع">7350</Row>


       <Row ty='W' id="الطماطم">6500</Row>
       <Row ty='W' id="الكوسا">0</Row>
       <Row ty='W' id="الباذنجان">0</Row>
       <Row ty='W' id="الخيار">7000</Row>
       <Row ty='W' id="الفلفل">0</Row>
       <Row ty='W' id="الخضروات الاخرى">6200</Row>

       </البدع>
    <حقل>
      <Row ty='W' id="نخيل البلح">11495</Row>
       <Row ty='W' id="الزيتون">0</Row>
       <Row ty='W' id="العنب">0</Row>
       <Row ty='W' id="الحمضيات">0</Row>
       <Row ty='W' id="التين">0</Row>
       <Row ty='W' id="الرمان">0</Row>
       <Row ty='W' id="خوخ">0</Row>
       <Row ty='W' id="مشمش">0</Row>
       <Row ty='W' id="تفاح">0</Row>
       <Row ty='W' id="المانجو">0</Row>
       <Row ty='W' id="اشجار اخرى+اشجار مختلطة">0</Row>
       <Row ty='W' id="الورد">0</Row>


       <Row ty='W' id="القمح">0</Row>
       <Row ty='W' id="الشعير">0</Row>
       <Row ty='W' id="الذرة الشامية">0</Row>
       <Row ty='W' id="الذرة الرفيعة">0 </Row>

       <Row ty='W' id="البرسيم">0</Row>
       <Row ty='W' id="الرودس">0 </Row>

       <Row ty='W' id="الطماطم">0</Row>
       <Row ty='W' id="الكوسا">0</Row>
       <Row ty='W' id="البطاطس">0</Row>
       <Row ty='W' id="الفاصوليا">0</Row>
       <Row ty='W' id="الفلفل">0</Row>
       <Row ty='W' id="الباذنجان">0</Row>
       <Row ty='W' id="ملفوف">0</Row>
       <Row ty='W' id="بصل">0</Row>
       <Row ty='W' id="جزر">0</Row>
       <Row ty='W' id="قرنبيط">0</Row>
       <Row ty='W' id="الخضروات الورقية">0 </Row>


       <Row ty='W' id="الطماطم">0</Row>
       <Row ty='W' id="بطاطس">0</Row>
       <Row ty='W' id="الفاصوليا">0</Row>
       <Row ty='W' id="الباميا">0</Row>
       <Row ty='W' id="الفلفل">0</Row>
       <Row ty='W' id="البصل">0</Row>
       <Row ty='W' id="البطيخ">0</Row>
       <Row ty='W' id="الشمام">0</Row>
       <Row ty='W' id="ملفوف">0</Row>
       <Row ty='W' id="الباذنجان">0</Row>
       <Row ty='W' id="القرع">0</Row>
       <Row ty='W' id="خيار">0</Row>
       <Row ty='W' id="الخضروات الورقيةاخرى">0</Row>
       <Row ty='W' id="النعناع">0</Row>


       <Row ty='W' id="الطماطم">0</Row>
       <Row ty='W' id="الكوسا">0</Row>
       <Row ty='W' id="الباذنجان">0</Row>
       <Row ty='W' id="الخيار">0</Row>
       <Row ty='W' id="الفلفل">0</Row>
       <Row ty='W' id="الخضروات الاخرى">0</Row>

       </حقل>




   </Records>
   <Records>
        <المحصول>
       <Row ty='E' id="0">نخيل البلح</Row>
       <Row ty='E' id="1">الزيتون</Row>
       <Row ty='E' id="2">العنب</Row>
       <Row ty='E' id="3">الحمضيات</Row>
       <Row ty='E' id="4">التين</Row>
       <Row ty='E' id="5">خوخ</Row>
       <Row ty='E' id="6">مشمش</Row>
       <Row ty='E' id="7">تفاح</Row>
       <Row ty='E' id="8">المانجو</Row>
       <Row ty='E' id="9">اشجار اخرى+اشجار مختلطة</Row>
       <Row ty='E' id="10">الورد</Row>

       <Row ty='E' id="11">القمح</Row>
       <Row ty='E' id="12">الشعير</Row>
       <Row ty='E' id="13">الذرة الشامية</Row>
       <Row ty='E' id="14">الذرة الرفيعة</Row>

     
       <Row ty='E' id="17">الطماطم</Row>
       <Row ty='E' id="18">الكوسا</Row>
       <Row ty='E' id="19">بطاطس</Row>
       <Row ty='E' id="20">الفاصوليا</Row>
       <Row ty='E' id="21">الفلفل</Row>
       <Row ty='E' id="22">الباذنجان</Row>
       <Row ty='E' id="23">ملفوف</Row>
       <Row ty='E' id="24">بصل</Row>
       <Row ty='E' id="25">جزر</Row>
       <Row ty='E' id="26">قرنبيط</Row>
       <Row ty='E' id="27">خضراوات ورقية اخرى</Row>

       <Row ty='E' id="28">الطماطم</Row>
       <Row ty='E' id="29">بطاطس</Row>
       <Row ty='E' id="30">الفاصوليا</Row>
       <Row ty='E' id="31">الباميا</Row>
       <Row ty='E' id="32">الفلفل</Row>
       <Row ty='E' id="33">بصل</Row>
       <Row ty='E' id="34">بطيخ</Row>
       <Row ty='E' id="35">الشمام</Row>
       <Row ty='E' id="36">ملفوف</Row>
       <Row ty='E' id="37">الباذنجان</Row>
       <Row ty='E' id="38">قرع</Row>
       <Row ty='E' id="39">خيار</Row>
       <Row ty='E' id="40">خضراوات ورقية اخرى</Row>
       <Row ty='E' id="41">النعناع</Row>


       <Row ty='E' id="42">الطماطم</Row>
       <Row ty='E' id="43">الكوسا</Row>
       <Row ty='E' id="44">الباذنجان</Row>
       <Row ty='E' id="45">الخيار</Row>
       <Row ty='E' id="46">الفلفل</Row>
       <Row ty='E' id="47">الباميا</Row>
       <Row ty='E' id="48">الخضروات الاخرى</Row>

       </المحصول>

       
       <تبوك>
   
       <Row ty='E' id="نخيل البلح">11.77</Row>
       <Row ty='E' id="الزيتون">10.37</Row>
       <Row ty='E' id="العنب">28.61</Row>
       <Row ty='E' id="الحمضيات">21.70</Row>
       <Row ty='E' id="التين">13.89</Row>
       <Row ty='E' id="الرمان">15.50</Row>
       <Row ty='E' id="خوخ">18.28</Row>
       <Row ty='E' id="مشمش">18.28</Row>
       <Row ty='E' id="تفاح">20.20</Row>
       <Row ty='E' id="المانجو">8.98</Row>
       <Row ty='E' id="اشجار اخرى+اشجار مختلطة">11.40</Row>
       <Row ty='E' id="الورد">2.20</Row>


       <Row ty='E' id="القمح">6.43</Row>
       <Row ty='E' id="الشعير">5.80</Row>
       <Row ty='E' id="الذرة الشامية">4.90</Row>
       <Row ty='E' id="الذرة الرفيعة">2.80</Row>

       <Row ty='E' id="البرسيم">20.12</Row>
       <Row ty='E' id="الرودس">20.80</Row>

       <Row ty='E' id="الطماطم">30.00</Row>
       <Row ty='E' id="الكوسا">0</Row>
       <Row ty='E' id="البطاطس">19.23</Row>
       <Row ty='E' id="الفاصوليا">10.50</Row>
       <Row ty='E' id="الفلفل">0</Row>
       <Row ty='E' id="الباذنجان">15.00</Row>
       <Row ty='E' id="ملفوف">25.37</Row>
       <Row ty='E' id="بصل">35.20</Row>
       <Row ty='E' id="جزر">24.20</Row>
       <Row ty='E' id="قرنبيط">18.56</Row>
       <Row ty='E' id="الخضروات الورقية">12.30 </Row>


       <Row ty='E' id="الطماطم">29.10</Row>
       <Row ty='E' id="بطاطس">22.23</Row>
       <Row ty='E' id="الفاصوليا">8.60</Row>
       <Row ty='E' id="الباميا">10.50</Row>
       <Row ty='E' id="الفلفل">13.88</Row>
       <Row ty='E' id="البصل">30.45</Row>
       <Row ty='E' id="البطيخ">24.60</Row>
       <Row ty='E' id="الشمام">23.10</Row>
       <Row ty='E' id="ملفوف">0</Row>
       <Row ty='E' id="الباذنجان">17.50</Row>
       <Row ty='E' id="القرع">28.20</Row>
       <Row ty='E' id="خيار">21.60</Row>
       <Row ty='E' id="الخضروات الورقيةاخرى">10.20</Row>
       <Row ty='E' id="النعناع">9.70</Row>


       <Row ty='E' id="الطماطم">115.20</Row>
       <Row ty='E' id="الكوسا">70.56</Row>
       <Row ty='E' id="الباذنجان">85.37</Row>
       <Row ty='E' id="الخيار">86.40</Row>
       <Row ty='E' id="الفلفل">61.92</Row>
       <Row ty='E' id="الخضروات الاخرى">64.80</Row>

       

       </تبوك>

        
       <الوجه>
        <Row ty='E' id="نخيل البلح">10.74</Row>
       <Row ty='E' id="الزيتون">0</Row>
       <Row ty='E' id="العنب">0</Row>
       <Row ty='E' id="الحمضيات">20.23</Row>
       <Row ty='E' id="التين">0</Row>
       <Row ty='E' id="الرمان">0</Row>
       <Row ty='E' id="خوخ">0</Row>
       <Row ty='E' id="مشمش">0</Row>
       <Row ty='E' id="تفاح">0</Row>
       <Row ty='E' id="المانجو">11.68</Row>
       <Row ty='E' id="اشجار اخرى+اشجار مختلطة">0</Row>
       <Row ty='E' id="الورد">0</Row>


       <Row ty='E' id="القمح">5.86</Row>
       <Row ty='E' id="الشعير">5.29</Row>
       <Row ty='E' id="الذرة الشامية">0</Row>
       <Row ty='E' id="الذرة الرفيعة">0</Row>

       <Row ty='E' id="البرسيم">0</Row>
       <Row ty='E' id="الرودس">0</Row>

       <Row ty='E' id="الطماطم">26.30</Row>
       <Row ty='E' id="الكوسا">13.07</Row>
       <Row ty='E' id="البطاطس">0.00</Row>
       <Row ty='E' id="الفاصوليا">0</Row>
       <Row ty='E' id="الفلفل">14.37</Row>
       <Row ty='E' id="الباذنجان">12.80</Row>
       <Row ty='E' id="ملفوف">0</Row>
       <Row ty='E' id="بصل">0</Row>
       <Row ty='E' id="جزر">22.07</Row>
       <Row ty='E' id="قرنبيط">16.93</Row>
       <Row ty='E' id="الخضروات الورقية">11.22 </Row>


       <Row ty='E' id="الطماطم">25.13</Row>
       <Row ty='E' id="بطاطس">0</Row>
       <Row ty='E' id="الفاصوليا">0</Row>
       <Row ty='E' id="الباميا">9.05</Row>
       <Row ty='E' id="الفلفل">12.66</Row>
       <Row ty='E' id="البصل">0</Row>
       <Row ty='E' id="البطيخ">22.08</Row>
       <Row ty='E' id="الشمام">0</Row>
       <Row ty='E' id="ملفوف">0</Row>
       <Row ty='E' id="الباذنجان">14.99</Row>
       <Row ty='E' id="القرع">0</Row>
       <Row ty='E' id="خيار">0</Row>
       <Row ty='E' id="الخضروات الورقيةاخرى">9.30</Row>
       <Row ty='E' id="النعناع">0</Row>


       <Row ty='E' id="الطماطم">0</Row>
       <Row ty='E' id="الكوسا">0</Row>
       <Row ty='E' id="الباذنجان">0</Row>
       <Row ty='E' id="الخيار">0</Row>
       <Row ty='E' id="الفلفل">0</Row>
       <Row ty='E' id="الخضروات الاخرى">0</Row>

       

       </الوجه>



        



       <ضباء>
       <Row ty='E' id="نخيل البلح">10.83</Row>
       <Row ty='E' id="الزيتون">9.77</Row>
       <Row ty='E' id="العنب">26.91</Row>
       <Row ty='E' id="الحمضيات">20.36</Row>
       <Row ty='E' id="التين">0</Row>
       <Row ty='E' id="الرمان">14.50</Row>
       <Row ty='E' id="خوخ">17.06</Row>
       <Row ty='E' id="مشمش">17.06</Row>
       <Row ty='E' id="تفاح">0</Row>
       <Row ty='E' id="المانجو">12.57</Row>
       <Row ty='E' id="اشجار اخرى+اشجار مختلطة">12.57</Row>
       <Row ty='E' id="الورد">0</Row>


       <Row ty='E' id="القمح">5.92</Row>
       <Row ty='E' id="الشعير">5.34</Row>
       <Row ty='E' id="الذرة الشامية">4.51</Row>
       <Row ty='E' id="الذرة الرفيعة">2.50</Row>

       <Row ty='E' id="البرسيم">0</Row>
       <Row ty='E' id="الرودس">0</Row>

       <Row ty='E' id="الطماطم">26.64</Row>
       <Row ty='E' id="الكوسا">13.18</Row>
       <Row ty='E' id="البطاطس">17.69</Row>
       <Row ty='E' id="الفاصوليا">9.66</Row>
       <Row ty='E' id="الفلفل">14.50</Row>
       <Row ty='E' id="الباذنجان">13.00</Row>
       <Row ty='E' id="ملفوف">23.34</Row>
       <Row ty='E' id="بصل">32.14</Row>
       <Row ty='E' id="جزر">22.26</Row>
       <Row ty='E' id="قرنبيط">17.08</Row>
       <Row ty='E' id="الخضروات الورقية">11.32 </Row>


       <Row ty='E' id="الطماطم">25.49</Row>
       <Row ty='E' id="بطاطس">20.45</Row>
       <Row ty='E' id="الفاصوليا">7.91</Row>
       <Row ty='E' id="الباميا">9.18</Row>
       <Row ty='E' id="الفلفل">12.77</Row>
       <Row ty='E' id="البصل">28.01</Row>
       <Row ty='E' id="البطيخ">22.31</Row>
       <Row ty='E' id="الشمام">21.25</Row>
       <Row ty='E' id="ملفوف">20.26</Row>
       <Row ty='E' id="الباذنجان">15.22</Row>
       <Row ty='E' id="القرع">25.94</Row>
       <Row ty='E' id="خيار">19.87</Row>
       <Row ty='E' id="الخضروات الورقيةاخرى">9.38</Row>
       <Row ty='E' id="النعناع">0</Row>


       <Row ty='E' id="الطماطم">0</Row>
       <Row ty='E' id="الكوسا">0</Row>
       <Row ty='E' id="الباذنجان">0</Row>
       <Row ty='E' id="الخيار">0</Row>
       <Row ty='E' id="الفلفل">0</Row>
       <Row ty='E' id="الخضروات الاخرى">0</Row>

       
       </ضباء>









       <تيماء>
        <Row ty='E' id="نخيل البلح">11.54</Row>
       <Row ty='E' id="الزيتون">10.23</Row>
       <Row ty='E' id="العنب">28.18</Row>
       <Row ty='E' id="الحمضيات">21.37</Row>
       <Row ty='E' id="التين">13.61</Row>
       <Row ty='E' id="الرمان">15.25</Row>
       <Row ty='E' id="خوخ">17.97</Row>
       <Row ty='E' id="مشمش">17.97</Row>
       <Row ty='E' id="تفاح">0</Row>
       <Row ty='E' id="المانجو">0</Row>
       <Row ty='E' id="اشجار اخرى+اشجار مختلطة">11.19</Row>
       <Row ty='E' id="الورد">2.16</Row>


       <Row ty='E' id="القمح">6.30</Row>
       <Row ty='E' id="الشعير">5.68</Row>
       <Row ty='E' id="الذرة الشامية">4.80</Row>
       <Row ty='E' id="الذرة الرفيعة">2.80</Row>

       <Row ty='E' id="البرسيم">19.72</Row>
       <Row ty='E' id="الرودس">20.38</Row>

       <Row ty='E' id="الطماطم">29.16</Row>
       <Row ty='E' id="الكوسا">14.04</Row>
       <Row ty='E' id="البطاطس">18.84</Row>
       <Row ty='E' id="الفاصوليا">0</Row>
       <Row ty='E' id="الفلفل">0</Row>
       <Row ty='E' id="الباذنجان">14.50</Row>
       <Row ty='E' id="ملفوف">24.86</Row>
       <Row ty='E' id="بصل">34.44</Row>
       <Row ty='E' id="جزر">23.72</Row>
       <Row ty='E' id="قرنبيط">18.19</Row>
       <Row ty='E' id="الخضروات الورقية">12.05 </Row>


       <Row ty='E' id="الطماطم">28.20</Row>
       <Row ty='E' id="بطاطس">0</Row>
       <Row ty='E' id="الفاصوليا">0</Row>
       <Row ty='E' id="الباميا">0</Row>
       <Row ty='E' id="الفلفل">13.60</Row>
       <Row ty='E' id="البصل">29.84</Row>
       <Row ty='E' id="البطيخ">0</Row>
       <Row ty='E' id="الشمام">0</Row>
       <Row ty='E' id="ملفوف">0</Row>
       <Row ty='E' id="الباذنجان">16.93</Row>
       <Row ty='E' id="القرع">0</Row>
       <Row ty='E' id="خيار">21.17</Row>
       <Row ty='E' id="الخضروات الورقيةاخرى">0</Row>
       <Row ty='E' id="النعناع">0</Row>


       <Row ty='E' id="الطماطم">112.90</Row>
       <Row ty='E' id="الكوسا">69.15</Row>
       <Row ty='E' id="الباذنجان">83.66</Row>
       <Row ty='E' id="الخيار">84.67</Row>
       <Row ty='E' id="الفلفل">0</Row>
       <Row ty='E' id="الخضروات الاخرى">0</Row>

       
       </تيماء>










       <املج>
       <Row ty='E' id="نخيل البلح">11.07</Row>
       <Row ty='E' id="الزيتون">9.91</Row>
       <Row ty='E' id="العنب">27.33</Row>
       <Row ty='E' id="الحمضيات">20.70</Row>
       <Row ty='E' id="التين">0</Row>
       <Row ty='E' id="الرمان">14.75</Row>
       <Row ty='E' id="خوخ">0</Row>
       <Row ty='E' id="مشمش">0</Row>
       <Row ty='E' id="تفاح">0</Row>
       <Row ty='E' id="المانجو">12.13</Row>
       <Row ty='E' id="اشجار اخرى+اشجار مختلطة">10.78</Row>
       <Row ty='E' id="الورد">0</Row>


       <Row ty='E' id="القمح">0</Row>
       <Row ty='E' id="الشعير">0</Row>
       <Row ty='E' id="الذرة الشامية">4.61</Row>
       <Row ty='E' id="الذرة الرفيعة">2.60</Row>

       <Row ty='E' id="البرسيم">0</Row>
       <Row ty='E' id="الرودس">0</Row>

       <Row ty='E' id="الطماطم">27.48</Row>
       <Row ty='E' id="الكوسا">0</Row>
       <Row ty='E' id="البطاطس">0.00</Row>
       <Row ty='E' id="الفاصوليا">0</Row>
       <Row ty='E' id="الفلفل">14.81</Row>
       <Row ty='E' id="الباذنجان">13.50</Row>
       <Row ty='E' id="ملفوف">0</Row>
       <Row ty='E' id="بصل">0</Row>
       <Row ty='E' id="جزر">0</Row>
       <Row ty='E' id="قرنبيط">17.45</Row>
       <Row ty='E' id="الخضروات الورقية">0</Row>


       <Row ty='E' id="الطماطم">26.39</Row>
       <Row ty='E' id="بطاطس">0</Row>
       <Row ty='E' id="الفاصوليا">0</Row>
       <Row ty='E' id="الباميا">9.51</Row>
       <Row ty='E' id="الفلفل">13.05</Row>
       <Row ty='E' id="البصل">0</Row>
       <Row ty='E' id="البطيخ">0</Row>
       <Row ty='E' id="الشمام">0</Row>
       <Row ty='E' id="ملفوف">0</Row>
       <Row ty='E' id="الباذنجان">15.79</Row>
       <Row ty='E' id="القرع">26.51</Row>
       <Row ty='E' id="خيار">0</Row>
       <Row ty='E' id="الخضروات الورقيةاخرى">9.59</Row>
       <Row ty='E' id="النعناع">0</Row>


       <Row ty='E' id="الطماطم">0</Row>
       <Row ty='E' id="الكوسا">0</Row>
       <Row ty='E' id="الباذنجان">0</Row>
       <Row ty='E' id="الخيار">0</Row>
       <Row ty='E' id="الفلفل">0</Row>
       <Row ty='E' id="الخضروات الاخرى">0</Row>

       
       </املج>












       <البدع>
       <Row ty='E' id="نخيل البلح">11.42</Row>
       <Row ty='E' id="الزيتون">10.15</Row>
       <Row ty='E' id="العنب">27.94</Row>
       <Row ty='E' id="الحمضيات">21.20</Row>
       <Row ty='E' id="التين">13.47</Row>
       <Row ty='E' id="الرمان">15.13</Row>
       <Row ty='E' id="خوخ">17.82</Row>
       <Row ty='E' id="مشمش">17.82</Row>
       <Row ty='E' id="تفاح">0</Row>
       <Row ty='E' id="المانجو">8.71</Row>
       <Row ty='E' id="اشجار اخرى+اشجار مختلطة">11.09</Row>
       <Row ty='E' id="الورد">0</Row>


       <Row ty='E' id="القمح">6.24</Row>
       <Row ty='E' id="الشعير">5.63</Row>
       <Row ty='E' id="الذرة الشامية">4.75</Row>
       <Row ty='E' id="الذرة الرفيعة">2.70</Row>

       <Row ty='E' id="البرسيم">0</Row>
       <Row ty='E' id="الرودس">0</Row>

       <Row ty='E' id="الطماطم">28.74</Row>
       <Row ty='E' id="الكوسا">13.90</Row>
       <Row ty='E' id="البطاطس">18.65</Row>
       <Row ty='E' id="الفاصوليا">10.19</Row>
       <Row ty='E' id="الفلفل">15.29</Row>
       <Row ty='E' id="الباذنجان">14.25</Row>
       <Row ty='E' id="ملفوف">24.61</Row>
       <Row ty='E' id="بصل">34.05</Row>
       <Row ty='E' id="جزر">23.47</Row>
       <Row ty='E' id="قرنبيط">18.00</Row>
       <Row ty='E' id="الخضروات الورقية">11.93 </Row>


       <Row ty='E' id="الطماطم">27.75</Row>
       <Row ty='E' id="بطاطس">0</Row>
       <Row ty='E' id="الفاصوليا">8.34</Row>
       <Row ty='E' id="الباميا">10.01</Row>
       <Row ty='E' id="الفلفل">13.46</Row>
       <Row ty='E' id="البصل">29.54</Row>
       <Row ty='E' id="البطيخ">23.74</Row>
       <Row ty='E' id="الشمام">22.41</Row>
       <Row ty='E' id="ملفوف">21.20</Row>
       <Row ty='E' id="الباذنجان">16.65</Row>
       <Row ty='E' id="القرع">27.35</Row>
       <Row ty='E' id="خيار">20.95</Row>
       <Row ty='E' id="الخضروات الورقيةاخرى">9.89</Row>
       <Row ty='E' id="النعناع">9.41</Row>


       <Row ty='E' id="الطماطم">111.74</Row>
       <Row ty='E' id="الكوسا">0</Row>
       <Row ty='E' id="الباذنجان">0</Row>
       <Row ty='E' id="الخيار">83.81</Row>
       <Row ty='E' id="الفلفل">0</Row>
       <Row ty='E' id="الخضروات الاخرى">62.86</Row>

       
       </البدع>





       <حقل>
       <Row ty='E' id="نخيل البلح">10.60</Row>
       <Row ty='E' id="الزيتون">0</Row>
       <Row ty='E' id="العنب">0</Row>
       <Row ty='E' id="الحمضيات">0</Row>
       <Row ty='E' id="التين">0</Row>
       <Row ty='E' id="الرمان">0</Row>
       <Row ty='E' id="خوخ">0</Row>
       <Row ty='E' id="مشمش">0</Row>
       <Row ty='E' id="تفاح">0</Row>
       <Row ty='E' id="المانجو">0</Row>
       <Row ty='E' id="اشجار اخرى+اشجار مختلطة">0</Row>
       <Row ty='E' id="الورد">0</Row>


       <Row ty='E' id="القمح">0</Row>
       <Row ty='E' id="الشعير">0</Row>
       <Row ty='E' id="الذرة الشامية">0</Row>
       <Row ty='E' id="الذرة الرفيعة">0</Row>

       <Row ty='E' id="البرسيم">0</Row>
       <Row ty='E' id="الرودس">0</Row>

       <Row ty='E' id="الطماطم">0</Row>
       <Row ty='E' id="الكوسا">0</Row>
       <Row ty='E' id="البطاطس">0</Row>
       <Row ty='E' id="الفاصوليا">0</Row>
       <Row ty='E' id="الفلفل">0</Row>
       <Row ty='E' id="الباذنجان">0</Row>
       <Row ty='E' id="ملفوف">0</Row>
       <Row ty='E' id="بصل">0</Row>
       <Row ty='E' id="جزر">0</Row>
       <Row ty='E' id="قرنبيط">0</Row>
       <Row ty='E' id="الخضروات الورقية">0 </Row>


       <Row ty='E' id="الطماطم">0</Row>
       <Row ty='E' id="بطاطس">0</Row>
       <Row ty='E' id="الفاصوليا">0</Row>
       <Row ty='E' id="الباميا">0</Row>
       <Row ty='E' id="الفلفل">0</Row>
       <Row ty='E' id="البصل">0</Row>
       <Row ty='E' id="البطيخ">0</Row>
       <Row ty='E' id="الشمام">0</Row>
       <Row ty='E' id="ملفوف">0</Row>
       <Row ty='E' id="الباذنجان">0</Row>
       <Row ty='E' id="القرع">0</Row>
       <Row ty='E' id="خيار">0</Row>
       <Row ty='E' id="الخضروات الورقيةاخرى">0</Row>
       <Row ty='E' id="النعناع">0</Row>


       <Row ty='E' id="الطماطم">0</Row>
       <Row ty='E' id="الكوسا">0</Row>
       <Row ty='E' id="الباذنجان">0</Row>
       <Row ty='E' id="الخيار">0</Row>
       <Row ty='E' id="الفلفل">0</Row>
       <Row ty='E' id="الخضروات الاخرى">0</Row>

       
       </حقل>
   </Records>
</rec>
